MANIFEST.in
setup.py
forgetmenot/__init__.py
forgetmenot/forgetmenot.glade
forgetmenot/gui.py
forgetmenot/quiz.py
forgetmenot/text.py
forgetmenot.egg-info/PKG-INFO
forgetmenot.egg-info/SOURCES.txt
forgetmenot.egg-info/dependency_links.txt
forgetmenot.egg-info/entry_points.txt
forgetmenot.egg-info/top_level.txt
forgetmenot.egg-info/zip-safe