Metadata-Version: 1.0
Name: forgetmenot
Version: 0.0.1
Summary: Simple flash card program
Home-page: http://bitbucket.org/trevor/forgetmenot
Author: Trevor Caira
Author-email: trevor@caira.com
License: UNKNOWN
Platform: UNKNOWN
